[{"domain": ".facebook.com", "expiry": 1745687979, "httpOnly": false, "name": "wd", "path": "/", "sameSite": "Lax", "secure": true, "value": "929x917"}, {"domain": ".facebook.com", "expiry": 1752859179, "httpOnly": true, "name": "fr", "path": "/", "sameSite": "None", "secure": true, "value": "0EjUVLSaE66AXVVxA..BoA9su..AAA.0.0.BoA9su.AWfnbEWeGy_om9FICoRHYbf1JJo"}, {"domain": ".facebook.com", "expiry": 1779643179, "httpOnly": true, "name": "datr", "path": "/", "sameSite": "None", "secure": true, "value": "LtsDaHv0lS5o-EB7zu6deBwf"}]